swarmk/kmeans.py
swarmk/main.py
swarmk/particle.py
swarmk/pso.py
swarmk/utils.py
swarmk-0.0.2.dist-info/METADATA
swarmk-0.0.2.dist-info/WHEEL
swarmk-0.0.2.dist-info/top_level.txt
swarmk-0.0.2.dist-info/RECORD
